{
  "User": [
    {
      "id": 1,
      "full_name": "Miguel Coutinho",
      "username": "miguel",
      "password": "admin",
      "email": "20311@stu.ipbeja.pt",
      "phone": "925873492",
      "NIF": "27282727277",
      "Seguro": "Multicare",
      "ADSE": "",
      "user_type": "1"
    },
    
    {
      "id": 2,
      "full_name": "Administrador",
      "username": "admin",
      "password": "123",
      "email": "admin@clinicapazinatto.pt",
      "phone": "000000000",
      "NIF": "000000000",
      "Seguro": "000000000",
      "ADSE": "000000000",
      "user_type": "1"
    },
    
    {
      "id": 3,
      "full_name": "Usuário",
      "username": "user",
      "password": "user",
      "email": "user@gmail.com",
      "phone": "987456213",
      "NIF": "654067432",
      "Seguro": "AdvanceCare",
      "ADSE": "000000000",
      "user_type": "2"
    } 
  ],
  
  "Treatment": [
      {
        "id": 1,
        "treatment_type": "Extração",
        "time": "60"
      },
    
      {
        "id": 2,
        "treatment_type": "Desvitalização",
        "time": "120"
      }
    ],
  
  "Appointment": [
      {
        "id": 1,
        "username": "miguel",
        "date_time": "11:15 - 12:00",
        "date_day":"1-1-2022"
      },
    
      {
        "id": 1,
        "username": "miguel",
        "date_time": "16:15 - 17:00",
        "date_day":"6-1-2022"
      },
         
      {
        "id": 3,
        "username": "user",
        "date_time": "15:15 - 16:00",
        "date_day":"2-1-2022"
      }
    ]
}
 
